Metadata-Version: 1.0
Name: fnet-pytorch
Version: 0.1.0
Summary: PyTorch implementation of Google's FNet
Home-page: https://github.com/erksch/fnet-pytorch
Author: UNKNOWN
Author-email: UNKNOWN
License: MIT License
Platform: UNKNOWN
